{".class":"MypyFile","_fullname":"libqtile.core.lifecycle","future_import_flags":[],"is_partial_stub_package":false,"is_stub":false,"names":{".class":"SymbolTable","Behavior":{".class":"SymbolTableNode","kind":"Gdef","module_public":false,"node":{".class":"TypeInfo","_promote":[],"abstract_attributes":[],"alt_promote":null,"bases":["enum.Enum"],"dataclass_transform_spec":null,"declared_metaclass":null,"defn":{".class":"ClassDef","fullname":"libqtile.core.lifecycle.Behavior","name":"Behavior","type_vars":[]},"deletable_attributes":[],"deprecated":null,"flags":["is_enum"],"fullname":"libqtile.core.lifecycle.Behavior","has_param_spec_type":false,"metaclass_type":"enum.EnumMeta","metadata":{},"module_name":"libqtile.core.lifecycle","mro":["libqtile.core.lifecycle.Behavior","enum.Enum","builtins.object"],"names":{".class":"SymbolTable","NONE":{".class":"SymbolTableNode","kind":"Mdef","node":{".class":"Var","flags":["is_property","is_ready","is_inferred","has_explicit_value"],"fullname":"libqtile.core.lifecycle.Behavior.NONE","name":"NONE","type":null}},"RESTART":{".class":"SymbolTableNode","kind":"Mdef","node":{".class":"Var","flags":["is_property","is_ready","is_inferred","has_explicit_value"],"fullname":"libqtile.core.lifecycle.Behavior.RESTART","name":"RESTART","type":null}},"TERMINATE":{".class":"SymbolTableNode","kind":"Mdef","node":{".class":"Var","flags":["is_property","is_ready","is_inferred","has_explicit_value"],"fullname":"libqtile.core.lifecycle.Behavior.TERMINATE","name":"TERMINATE","type":null}}},"self_type":null,"slots":null,"tuple_type":null,"type_vars":[],"typeddict_type":null}},"LifeCycle":{".class":"SymbolTableNode","kind":"Gdef","module_public":false,"node":{".class":"TypeInfo","_promote":[],"abstract_attributes":[],"alt_promote":null,"bases":["builtins.object"],"dataclass_transform_spec":null,"declared_metaclass":null,"defn":{".class":"ClassDef","fullname":"libqtile.core.lifecycle.LifeCycle","name":"LifeCycle","type_vars":[]},"deletable_attributes":[],"deprecated":null,"flags":[],"fullname":"libqtile.core.lifecycle.LifeCycle","has_param_spec_type":false,"metaclass_type":null,"metadata":{},"module_name":"libqtile.core.lifecycle","mro":["libqtile.core.lifecycle.LifeCycle","builtins.object"],"names":{".class":"SymbolTable","__init__":{".class":"SymbolTableNode","kind":"Mdef","node":{".class":"FuncDef","abstract_status":0,"arg_kinds":[0],"arg_names":["self"],"dataclass_transform_spec":null,"deprecated":null,"flags":[],"fullname":"libqtile.core.lifecycle.LifeCycle.__init__","name":"__init__","type":{".class":"CallableType","arg_kinds":[0],"arg_names":["self"],"arg_types":["libqtile.core.lifecycle.LifeCycle"],"bound_args":[],"def_extras":{"first_arg":"self"},"fallback":"builtins.function","from_concatenate":false,"implicit":false,"imprecise_arg_kinds":false,"is_ellipsis_args":false,"name":"__init__ of LifeCycle","ret_type":{".class":"NoneType"},"type_guard":null,"type_is":null,"unpack_kwargs":false,"variables":[]}}},"_atexit":{".class":"SymbolTableNode","kind":"Mdef","node":{".class":"FuncDef","abstract_status":0,"arg_kinds":[0],"arg_names":["self"],"dataclass_transform_spec":null,"deprecated":null,"flags":[],"fullname":"libqtile.core.lifecycle.LifeCycle._atexit","name":"_atexit","type":{".class":"CallableType","arg_kinds":[0],"arg_names":["self"],"arg_types":["libqtile.core.lifecycle.LifeCycle"],"bound_args":[],"def_extras":{"first_arg":"self"},"fallback":"builtins.function","from_concatenate":false,"implicit":false,"imprecise_arg_kinds":false,"is_ellipsis_args":false,"name":"_atexit of LifeCycle","ret_type":{".class":"NoneType"},"type_guard":null,"type_is":null,"unpack_kwargs":false,"variables":[]}}},"behavior":{".class":"SymbolTableNode","implicit":true,"kind":"Mdef","node":{".class":"Var","flags":["is_inferred"],"fullname":"libqtile.core.lifecycle.LifeCycle.behavior","name":"behavior","type":"libqtile.core.lifecycle.Behavior"}},"exitcode":{".class":"SymbolTableNode","implicit":true,"kind":"Mdef","node":{".class":"Var","flags":["explicit_self_type","is_ready","is_inferred"],"fullname":"libqtile.core.lifecycle.LifeCycle.exitcode","name":"exitcode","type":"builtins.int"}},"state_file":{".class":"SymbolTableNode","implicit":true,"kind":"Mdef","node":{".class":"Var","flags":["explicit_self_type","is_ready","is_inferred"],"fullname":"libqtile.core.lifecycle.LifeCycle.state_file","name":"state_file","type":{".class":"UnionType","items":["builtins.str",{".class":"NoneType"}],"uses_pep604_syntax":true}}}},"self_type":{".class":"TypeVarType","default":{".class":"AnyType","missing_import_name":null,"source_any":null,"type_of_any":4},"fullname":"libqtile.core.lifecycle.LifeCycle.Self","id":0,"name":"Self","namespace":"","upper_bound":"libqtile.core.lifecycle.LifeCycle","values":[],"variance":0},"slots":null,"tuple_type":null,"type_vars":[],"typeddict_type":null}},"__all__":{".class":"SymbolTableNode","kind":"Gdef","module_public":false,"node":{".class":"Var","flags":["is_inferred","has_explicit_value"],"fullname":"libqtile.core.lifecycle.__all__","name":"__all__","type":{".class":"Instance","args":["builtins.str"],"extra_attrs":null,"type_ref":"builtins.list"}}},"__annotations__":{".class":"SymbolTableNode","kind":"Gdef","module_public":false,"node":{".class":"Var","flags":["is_ready"],"fullname":"libqtile.core.lifecycle.__annotations__","name":"__annotations__","type":{".class":"Instance","args":["builtins.str",{".class":"AnyType","missing_import_name":null,"source_any":null,"type_of_any":6}],"extra_attrs":null,"type_ref":"builtins.dict"}}},"__doc__":{".class":"SymbolTableNode","kind":"Gdef","module_public":false,"node":{".class":"Var","flags":["is_ready"],"fullname":"libqtile.core.lifecycle.__doc__","name":"__doc__","type":"builtins.str"}},"__file__":{".class":"SymbolTableNode","kind":"Gdef","module_public":false,"node":{".class":"Var","flags":["is_ready"],"fullname":"libqtile.core.lifecycle.__file__","name":"__file__","type":"builtins.str"}},"__name__":{".class":"SymbolTableNode","kind":"Gdef","module_public":false,"node":{".class":"Var","flags":["is_ready"],"fullname":"libqtile.core.lifecycle.__name__","name":"__name__","type":"builtins.str"}},"__package__":{".class":"SymbolTableNode","kind":"Gdef","module_public":false,"node":{".class":"Var","flags":["is_ready"],"fullname":"libqtile.core.lifecycle.__package__","name":"__package__","type":"builtins.str"}},"__spec__":{".class":"SymbolTableNode","kind":"Gdef","module_public":false,"node":{".class":"Var","flags":["is_ready"],"fullname":"libqtile.core.lifecycle.__spec__","name":"__spec__","type":"_frozen_importlib.ModuleSpec"}},"atexit":{".class":"SymbolTableNode","cross_ref":"atexit","kind":"Gdef","module_public":false},"enum":{".class":"SymbolTableNode","cross_ref":"enum","kind":"Gdef","module_public":false},"lifecycle":{".class":"SymbolTableNode","kind":"Gdef","node":{".class":"Var","flags":["is_inferred","has_explicit_value"],"fullname":"libqtile.core.lifecycle.lifecycle","name":"lifecycle","type":"libqtile.core.lifecycle.LifeCycle"}},"logger":{".class":"SymbolTableNode","cross_ref":"libqtile.log_utils.logger","kind":"Gdef","module_public":false},"os":{".class":"SymbolTableNode","cross_ref":"os","kind":"Gdef","module_public":false},"sys":{".class":"SymbolTableNode","cross_ref":"sys","kind":"Gdef","module_public":false}},"path":"/usr/lib64/python3.13/site-packages/libqtile/core/lifecycle.py"}